fw_gear_fsl_fslhd/__init__.py
fw_gear_fsl_fslhd/interfaces.py
fw_gear_fsl_fslhd/main.py
fw_gear_fsl_fslhd/parser.py
fw_gear_fsl_fslhd-1.1.3.dist-info/LICENSE
fw_gear_fsl_fslhd-1.1.3.dist-info/WHEEL
fw_gear_fsl_fslhd-1.1.3.dist-info/METADATA
fw_gear_fsl_fslhd-1.1.3.dist-info/RECORD
